odoo/addons/stock_vertical_lift_storage_type/README.rst
odoo/addons/stock_vertical_lift_storage_type/__init__.py
odoo/addons/stock_vertical_lift_storage_type/__manifest__.py
odoo/addons/stock_vertical_lift_storage_type/i18n/stock_vertical_lift_storage_type.pot
odoo/addons/stock_vertical_lift_storage_type/models/__init__.py
odoo/addons/stock_vertical_lift_storage_type/models/stock_location.py
odoo/addons/stock_vertical_lift_storage_type/models/stock_location_tray_type.py
odoo/addons/stock_vertical_lift_storage_type/models/stock_quant.py
odoo/addons/stock_vertical_lift_storage_type/models/vertical_lift_operation_put.py
odoo/addons/stock_vertical_lift_storage_type/readme/CONTRIBUTORS.rst
odoo/addons/stock_vertical_lift_storage_type/readme/DESCRIPTION.rst
odoo/addons/stock_vertical_lift_storage_type/static/description/icon.png
odoo/addons/stock_vertical_lift_storage_type/static/description/index.html
odoo/addons/stock_vertical_lift_storage_type/tests/__init__.py
odoo/addons/stock_vertical_lift_storage_type/tests/common.py
odoo/addons/stock_vertical_lift_storage_type/tests/test_put.py
odoo/addons/stock_vertical_lift_storage_type/tests/test_stock_location.py
odoo/addons/stock_vertical_lift_storage_type/tests/test_tray_type.py
odoo/addons/stock_vertical_lift_storage_type/views/stock_location_tray_type_views.xml
odoo/addons/stock_vertical_lift_storage_type/views/stock_location_views.xml
odoo13_addon_stock_vertical_lift_storage_type-13.0.1.0.1.dev6.dist-info/METADATA
odoo13_addon_stock_vertical_lift_storage_type-13.0.1.0.1.dev6.dist-info/WHEEL
odoo13_addon_stock_vertical_lift_storage_type-13.0.1.0.1.dev6.dist-info/top_level.txt
odoo13_addon_stock_vertical_lift_storage_type-13.0.1.0.1.dev6.dist-info/RECORD
